<?xml version="1.0" encoding="UTF-8"?><Root><Header><ServCode>predealInterfaceBO.getActivityId</ServCode><Time>2016-03-11 17:53:57</Time></Header><Body><service><data_info><result_flag>1</result_flag><result>查询成功!</result><sessionId>1778476643</sessionId><processId>15081641</processId><processInstanceId>1778476645</processInstanceId><tacticInstanceId>15081641</tacticInstanceId><actList><activityId>IDA_BSS_CHECK_USERSTATUS</activityId><activityName>检查BSS用户状态是否异常</activityName><catalogId>1</catalogId><catalogDesc>业务平台</catalogDesc><infSrc>crmQuery</infSrc><execType>bsh</execType><resultView>业务平台</resultView><dependActivityId/><dependAtResultId>null</dependAtResultId></actList><actList><activityId>IDA_IPOSS_OLT_DEV</activityId><activityName>接入设备（OLT）状态</activityName><catalogId>2</catalogId><catalogDesc>接入侧</catalogDesc><infSrc>ipossEponQueryService</infSrc><execType>bsh</execType><resultView>接入侧</resultView><dependActivityId/><dependAtResultId>null</dependAtResultId></actList><actList><activityId>IDA_IPOSS_ONU_USER_DEV</activityId><activityName>ONU用户端口是否正常</activityName><catalogId>21</catalogId><catalogDesc>用户侧</catalogDesc><infSrc>ipossEponQueryService</infSrc><execType>bsh</execType><resultView>用户侧</resultView><dependActivityId/><dependAtResultId>null</dependAtResultId></actList><actList><activityId>IDA_ITMS_ONU_TERM_INTERA</activityId><activityName>E8-C终端是否能交互</activityName><catalogId>6</catalogId><catalogDesc>用户侧</catalogDesc><infSrc>itmsQueryDeviceConfig</infSrc><execType>bsh</execType><resultView>用户侧</resultView><dependActivityId/><dependAtResultId>null</dependAtResultId></actList><actList><activityId>IDA_RADIUS_CHECK_ONLINE</activityId><activityName>宽带用户帐号是否在线</activityName><catalogId>3</catalogId><catalogDesc>业务平台</catalogDesc><infSrc>bssInfoQueryByNumber</infSrc><execType>bsh</execType><resultView>业务平台</resultView><dependActivityId/><dependAtResultId>null</dependAtResultId></actList><actList><activityId>IDA_RADIUS_CHECK_7DAYS_ERRINFO</activityId><activityName>检查RADIUS最近一周是否有错误提示</activityName><catalogId>3</catalogId><catalogDesc>业务平台</catalogDesc><infSrc>bssInfoQueryByNumber</infSrc><execType>bsh</execType><resultView>业务平台</resultView><dependActivityId>IDA_RADIUS_CHECK_ERRINFO</dependActivityId><dependAtResultId>14</dependAtResultId></actList><actList><activityId>IDA_RADIUS_CHECK_ERRINFO</activityId><activityName>检查RADIUS是否当天有错误提示</activityName><catalogId>3</catalogId><catalogDesc>业务平台</catalogDesc><infSrc>bssInfoQueryByNumber</infSrc><execType>bsh</execType><resultView>业务平台</resultView><dependActivityId/><dependAtResultId>null</dependAtResultId></actList><actList><activityId>IDA_ITMS_ONU_SOFTVER</activityId><activityName>E8-C终端软件版本是否规范</activityName><catalogId>6</catalogId><catalogDesc>用户侧</catalogDesc><infSrc>E8-C</infSrc><execType>bsh</execType><resultView>用户侧</resultView><dependActivityId/><dependAtResultId>null</dependAtResultId></actList><actList><activityId>IDA_IMS_ITMS_VOIP</activityId><activityName>比对用户VOIP帐号密码</activityName><catalogId>7</catalogId><catalogDesc>核心网</catalogDesc><infSrc/><execType>bsh</execType><resultView>核心网</resultView><dependActivityId/><dependAtResultId>null</dependAtResultId></actList><actList><activityId>IDA_IPOSS_OS_DEV</activityId><activityName>分光器到终端是否正常</activityName><catalogId>2</catalogId><catalogDesc>接入侧</catalogDesc><infSrc>ipossEponQueryService</infSrc><execType>bsh</execType><resultView>接入侧</resultView><dependActivityId/><dependAtResultId>null</dependAtResultId></actList><actList><activityId>IDA_RADIUS_CHECK_VLAN</activityId><activityName>核实错误信息中的vlan与BSS是否一致</activityName><catalogId>3</catalogId><catalogDesc>业务平台</catalogDesc><infSrc>crmQuery,radiusUserInfoQuery,bssInfoQueryByNumber</infSrc><execType>bsh</execType><resultView>业务平台</resultView><dependActivityId>IDA_RADIUS_CHECK_ERRINFO</dependActivityId><dependAtResultId>15</dependAtResultId></actList><actList><activityId>IDA_IPOSS_PON_LIGHTDECAY</activityId><activityName>用户PON口光衰是否正常</activityName><catalogId>2</catalogId><catalogDesc>接入侧</catalogDesc><infSrc>ipossEponQueryService</infSrc><execType>bsh</execType><resultView>接入侧</resultView><dependActivityId/><dependAtResultId>null</dependAtResultId></actList><actList><activityId>IDA_RADIUS_CHECK_MAC</activityId><activityName>核对在线记录中不同mac地址条数未超过规定终端数</activityName><catalogId>3</catalogId><catalogDesc>业务平台</catalogDesc><infSrc>bssInfoQueryByNumber</infSrc><execType>bsh</execType><resultView>业务平台</resultView><dependActivityId>IDA_RADIUS_CHECK_ERRINFO</dependActivityId><dependAtResultId>16</dependAtResultId></actList><actList><activityId>IDA_IPOSS_BSS_RESOURCE_CMP</activityId><activityName>PON资源跟BSS是否一致</activityName><catalogId>2</catalogId><catalogDesc>接入侧</catalogDesc><infSrc/><execType>bsh</execType><resultView>接入侧</resultView><dependActivityId/><dependAtResultId>null</dependAtResultId></actList><actList><activityId>IDA_ITMS_ONU_SOFTVER</activityId><activityName>E8-C终端软件版本是否规范</activityName><catalogId>6</catalogId><catalogDesc>用户侧</catalogDesc><infSrc>E8-C</infSrc><execType>bsh</execType><resultView>用户侧</resultView><dependActivityId/><dependAtResultId>null</dependAtResultId></actList></data_info><status>200 OK</status></service></Body></Root>